pysimplesocket/__init__.py
pysimplesocket/errors.py
pysimplesocket/sockets.py
pysimplesocket-0.1.0.dist-info/LICENSE
pysimplesocket-0.1.0.dist-info/METADATA
pysimplesocket-0.1.0.dist-info/WHEEL
pysimplesocket-0.1.0.dist-info/top_level.txt
pysimplesocket-0.1.0.dist-info/RECORD
