Metadata-Version: 2.1
Name: pysimplesocket
Version: 0.1.0
Summary: python simple socket
Home-page: https://github.com/LamentXU123/pySimpleSocket
Author: ['LamentXU', 'Meteor_Kai']
Author-email: ['1372449351@qq.com', '1318723916@qq.com']
License: MIT
Classifier: License :: OSI Approved :: MIT License
Classifier: Programming Language :: Python
Classifier: Programming Language :: Python :: 3
Classifier: Programming Language :: Python :: 3.6
Classifier: Programming Language :: Python :: Implementation :: CPython
Classifier: Programming Language :: Python :: Implementation :: PyPy
Requires-Python: >=3.6.0
License-File: LICENSE
